neurofeatures/__init__.py
neurofeatures/__main__.py
neurofeatures/neurofeatures.py
neurofeatures-0.0.1.dist-info/DESCRIPTION.rst
neurofeatures-0.0.1.dist-info/METADATA
neurofeatures-0.0.1.dist-info/RECORD
neurofeatures-0.0.1.dist-info/WHEEL
neurofeatures-0.0.1.dist-info/entry_points.txt
neurofeatures-0.0.1.dist-info/metadata.json
neurofeatures-0.0.1.dist-info/top_level.txt
